{
  "item": [
    {
      "id": "82949ab6-9e01-4b56-8931-8e77d4d453fb",
      "name": "Pipelines",
      "description": {
        "content": "Scheduled MQL aggregation pipelines.",
        "type": "text/plain"
      },
      "item": [
        {
          "id": "6028bd0c-3509-47b0-b865-4e5a27a52689",
          "name": "Viam Get Data Pipeline",
          "request": {
            "name": "Viam Get Data Pipeline",
            "description": {
              "content": "Retrieve a data pipeline by id.",
              "type": "text/plain"
            },
            "url": {
              "path": [
                "viam.app.datapipelines.v1.DataPipelinesService",
                "GetDataPipeline"
              ],
              "host": [
                "{{baseUrl}}"
              ],
              "query": [],
              "variable": []
            },
            "header": [
              {
                "key": "Content-Type",
                "value": "application/json"
              }
            ],
            "method": "POST",
            "auth": null,
            "body": {
              "mode": "raw",
              "raw": "{\n  \"id\": \"<string>\"\n}",
              "options": {
                "raw": {
                  "language": "json"
                }
              }
            }
          },
          "response": [
            {
              "id": "e023a5de-9642-4ffa-9c1d-4f5a2d25da4b",
              "name": "Successful response.",
              "originalRequest": {
                "url": {
                  "path": [
                    "viam.app.datapipelines.v1.DataPipelinesService",
                    "GetDataPipeline"
                  ],
                  "host": [
                    "{{baseUrl}}"
                  ],
                  "query": [],
                  "variable": []
                },
                "header": [
                  {
                    "description": {
                      "content": "Added as a part of security scheme: apikey",
                      "type": "text/plain"
                    },
                    "key": "key",
                    "value": "<API Key>"
                  }
                ],
                "method": "POST",
                "body": {
                  "mode": "raw",
                  "raw": "{\n  \"id\": \"<string>\"\n}",
                  "options": {
                    "raw": {
                      "language": "json"
                    }
                  }
                }
              },
              "status": "OK",
              "code": 200,
              "header": [
                {
                  "key": "Content-Type",
                  "value": "text/plain"
                }
              ],
              "body": "",
              "cookie": [],
              "_postman_previewlanguage": "text"
            }
          ],
          "event": [],
          "protocolProfileBehavior": {
            "disableBodyPruning": true
          }
        },
        {
          "id": "eefd5e74-383f-4ab5-adfc-e9790c3962ed",
          "name": "Viam List Data Pipelines",
          "request": {
            "name": "Viam List Data Pipelines",
            "description": {
              "content": "List data pipelines in an organization.",
              "type": "text/plain"
            },
            "url": {
              "path": [
                "viam.app.datapipelines.v1.DataPipelinesService",
                "ListDataPipelines"
              ],
              "host": [
                "{{baseUrl}}"
              ],
              "query": [],
              "variable": []
            },
            "header": [
              {
                "key": "Content-Type",
                "value": "application/json"
              }
            ],
            "method": "POST",
            "auth": null,
            "body": {
              "mode": "raw",
              "raw": "{\n  \"organization_id\": \"<string>\"\n}",
              "options": {
                "raw": {
                  "language": "json"
                }
              }
            }
          },
          "response": [
            {
              "id": "a0ac937a-f659-4aa4-87e3-6eb3b104ceba",
              "name": "Successful response.",
              "originalRequest": {
                "url": {
                  "path": [
                    "viam.app.datapipelines.v1.DataPipelinesService",
                    "ListDataPipelines"
                  ],
                  "host": [
                    "{{baseUrl}}"
                  ],
                  "query": [],
                  "variable": []
                },
                "header": [
                  {
                    "description": {
                      "content": "Added as a part of security scheme: apikey",
                      "type": "text/plain"
                    },
                    "key": "key",
                    "value": "<API Key>"
                  }
                ],
                "method": "POST",
                "body": {
                  "mode": "raw",
                  "raw": "{\n  \"organization_id\": \"<string>\"\n}",
                  "options": {
                    "raw": {
                      "language": "json"
                    }
                  }
                }
              },
              "status": "OK",
              "code": 200,
              "header": [
                {
                  "key": "Content-Type",
                  "value": "text/plain"
                }
              ],
              "body": "",
              "cookie": [],
              "_postman_previewlanguage": "text"
            }
          ],
          "event": [],
          "protocolProfileBehavior": {
            "disableBodyPruning": true
          }
        },
        {
          "id": "470e00d7-2c1b-435a-8265-10a49f2415d7",
          "name": "Viam Create Data Pipeline",
          "request": {
            "name": "Viam Create Data Pipeline",
            "description": {
              "content": "Create a new MQL data pipeline.",
              "type": "text/plain"
            },
            "url": {
              "path": [
                "viam.app.datapipelines.v1.DataPipelinesService",
                "CreateDataPipeline"
              ],
              "host": [
                "{{baseUrl}}"
              ],
              "query": [],
              "variable": []
            },
            "header": [
              {
                "key": "Content-Type",
                "value": "application/json"
              }
            ],
            "method": "POST",
            "auth": null,
            "body": {
              "mode": "raw",
              "raw": "{\n  \"organization_id\": \"<string>\",\n  \"name\": \"<string>\",\n  \"mql_binary\": [\n    \"<byte>\",\n    \"<byte>\"\n  ],\n  \"schedule\": \"<string>\"\n}",
              "options": {
                "raw": {
                  "language": "json"
                }
              }
            }
          },
          "response": [
            {
              "id": "accface2-ef44-44e8-941f-d2d1e4e876ad",
              "name": "Successful response.",
              "originalRequest": {
                "url": {
                  "path": [
                    "viam.app.datapipelines.v1.DataPipelinesService",
                    "CreateDataPipeline"
                  ],
                  "host": [
                    "{{baseUrl}}"
                  ],
                  "query": [],
                  "variable": []
                },
                "header": [
                  {
                    "description": {
                      "content": "Added as a part of security scheme: apikey",
                      "type": "text/plain"
                    },
                    "key": "key",
                    "value": "<API Key>"
                  }
                ],
                "method": "POST",
                "body": {
                  "mode": "raw",
                  "raw": "{\n  \"organization_id\": \"<string>\",\n  \"name\": \"<string>\",\n  \"mql_binary\": [\n    \"<byte>\",\n    \"<byte>\"\n  ],\n  \"schedule\": \"<string>\"\n}",
                  "options": {
                    "raw": {
                      "language": "json"
                    }
                  }
                }
              },
              "status": "OK",
              "code": 200,
              "header": [
                {
                  "key": "Content-Type",
                  "value": "text/plain"
                }
              ],
              "body": "",
              "cookie": [],
              "_postman_previewlanguage": "text"
            }
          ],
          "event": [],
          "protocolProfileBehavior": {
            "disableBodyPruning": true
          }
        },
        {
          "id": "6901d9c4-067c-46dc-8d3c-46d620d7ef2f",
          "name": "Viam Rename Data Pipeline",
          "request": {
            "name": "Viam Rename Data Pipeline",
            "description": {
              "content": "Rename a data pipeline.",
              "type": "text/plain"
            },
            "url": {
              "path": [
                "viam.app.datapipelines.v1.DataPipelinesService",
                "RenameDataPipeline"
              ],
              "host": [
                "{{baseUrl}}"
              ],
              "query": [],
              "variable": []
            },
            "header": [
              {
                "key": "Content-Type",
                "value": "application/json"
              }
            ],
            "method": "POST",
            "auth": null,
            "body": {
              "mode": "raw",
              "raw": "{\n  \"id\": \"<string>\",\n  \"name\": \"<string>\"\n}",
              "options": {
                "raw": {
                  "language": "json"
                }
              }
            }
          },
          "response": [
            {
              "id": "6fa1ebe0-a4df-46ed-8e00-ad00acabf7cd",
              "name": "Successful response.",
              "originalRequest": {
                "url": {
                  "path": [
                    "viam.app.datapipelines.v1.DataPipelinesService",
                    "RenameDataPipeline"
                  ],
                  "host": [
                    "{{baseUrl}}"
                  ],
                  "query": [],
                  "variable": []
                },
                "header": [
                  {
                    "description": {
                      "content": "Added as a part of security scheme: apikey",
                      "type": "text/plain"
                    },
                    "key": "key",
                    "value": "<API Key>"
                  }
                ],
                "method": "POST",
                "body": {
                  "mode": "raw",
                  "raw": "{\n  \"id\": \"<string>\",\n  \"name\": \"<string>\"\n}",
                  "options": {
                    "raw": {
                      "language": "json"
                    }
                  }
                }
              },
              "status": "OK",
              "code": 200,
              "header": [
                {
                  "key": "Content-Type",
                  "value": "text/plain"
                }
              ],
              "body": "",
              "cookie": [],
              "_postman_previewlanguage": "text"
            }
          ],
          "event": [],
          "protocolProfileBehavior": {
            "disableBodyPruning": true
          }
        },
        {
          "id": "d9360459-0f76-47ed-b275-4f1445021a51",
          "name": "Viam Delete Data Pipeline",
          "request": {
            "name": "Viam Delete Data Pipeline",
            "description": {
              "content": "Delete a data pipeline.",
              "type": "text/plain"
            },
            "url": {
              "path": [
                "viam.app.datapipelines.v1.DataPipelinesService",
                "DeleteDataPipeline"
              ],
              "host": [
                "{{baseUrl}}"
              ],
              "query": [],
              "variable": []
            },
            "header": [
              {
                "key": "Content-Type",
                "value": "application/json"
              }
            ],
            "method": "POST",
            "auth": null,
            "body": {
              "mode": "raw",
              "raw": "{\n  \"id\": \"<string>\"\n}",
              "options": {
                "raw": {
                  "language": "json"
                }
              }
            }
          },
          "response": [
            {
              "id": "539055ab-7aa2-44a2-bcd0-9df90c59baa6",
              "name": "Successful response.",
              "originalRequest": {
                "url": {
                  "path": [
                    "viam.app.datapipelines.v1.DataPipelinesService",
                    "DeleteDataPipeline"
                  ],
                  "host": [
                    "{{baseUrl}}"
                  ],
                  "query": [],
                  "variable": []
                },
                "header": [
                  {
                    "description": {
                      "content": "Added as a part of security scheme: apikey",
                      "type": "text/plain"
                    },
                    "key": "key",
                    "value": "<API Key>"
                  }
                ],
                "method": "POST",
                "body": {
                  "mode": "raw",
                  "raw": "{\n  \"id\": \"<string>\"\n}",
                  "options": {
                    "raw": {
                      "language": "json"
                    }
                  }
                }
              },
              "status": "OK",
              "code": 200,
              "header": [
                {
                  "key": "Content-Type",
                  "value": "text/plain"
                }
              ],
              "body": "",
              "cookie": [],
              "_postman_previewlanguage": "text"
            }
          ],
          "event": [],
          "protocolProfileBehavior": {
            "disableBodyPruning": true
          }
        },
        {
          "id": "e0e7a00c-7ddf-4a97-b090-5762ac6dea4a",
          "name": "Viam Enable Data Pipeline",
          "request": {
            "name": "Viam Enable Data Pipeline",
            "description": {
              "content": "Enable a paused data pipeline.",
              "type": "text/plain"
            },
            "url": {
              "path": [
                "viam.app.datapipelines.v1.DataPipelinesService",
                "EnableDataPipeline"
              ],
              "host": [
                "{{baseUrl}}"
              ],
              "query": [],
              "variable": []
            },
            "header": [
              {
                "key": "Content-Type",
                "value": "application/json"
              }
            ],
            "method": "POST",
            "auth": null,
            "body": {
              "mode": "raw",
              "raw": "{\n  \"id\": \"<string>\"\n}",
              "options": {
                "raw": {
                  "language": "json"
                }
              }
            }
          },
          "response": [
            {
              "id": "d90db46c-cabc-4818-abf2-72a2e7958f83",
              "name": "Successful response.",
              "originalRequest": {
                "url": {
                  "path": [
                    "viam.app.datapipelines.v1.DataPipelinesService",
                    "EnableDataPipeline"
                  ],
                  "host": [
                    "{{baseUrl}}"
                  ],
                  "query": [],
                  "variable": []
                },
                "header": [
                  {
                    "description": {
                      "content": "Added as a part of security scheme: apikey",
                      "type": "text/plain"
                    },
                    "key": "key",
                    "value": "<API Key>"
                  }
                ],
                "method": "POST",
                "body": {
                  "mode": "raw",
                  "raw": "{\n  \"id\": \"<string>\"\n}",
                  "options": {
                    "raw": {
                      "language": "json"
                    }
                  }
                }
              },
              "status": "OK",
              "code": 200,
              "header": [
                {
                  "key": "Content-Type",
                  "value": "text/plain"
                }
              ],
              "body": "",
              "cookie": [],
              "_postman_previewlanguage": "text"
            }
          ],
          "event": [],
          "protocolProfileBehavior": {
            "disableBodyPruning": true
          }
        },
        {
          "id": "b4ddb318-c617-4852-a202-867168b3e6d7",
          "name": "Viam Disable Data Pipeline",
          "request": {
            "name": "Viam Disable Data Pipeline",
            "description": {
              "content": "Disable a running data pipeline.",
              "type": "text/plain"
            },
            "url": {
              "path": [
                "viam.app.datapipelines.v1.DataPipelinesService",
                "DisableDataPipeline"
              ],
              "host": [
                "{{baseUrl}}"
              ],
              "query": [],
              "variable": []
            },
            "header": [
              {
                "key": "Content-Type",
                "value": "application/json"
              }
            ],
            "method": "POST",
            "auth": null,
            "body": {
              "mode": "raw",
              "raw": "{\n  \"id\": \"<string>\"\n}",
              "options": {
                "raw": {
                  "language": "json"
                }
              }
            }
          },
          "response": [
            {
              "id": "96a79257-3d83-46fd-a9b4-2c192e365eca",
              "name": "Successful response.",
              "originalRequest": {
                "url": {
                  "path": [
                    "viam.app.datapipelines.v1.DataPipelinesService",
                    "DisableDataPipeline"
                  ],
                  "host": [
                    "{{baseUrl}}"
                  ],
                  "query": [],
                  "variable": []
                },
                "header": [
                  {
                    "description": {
                      "content": "Added as a part of security scheme: apikey",
                      "type": "text/plain"
                    },
                    "key": "key",
                    "value": "<API Key>"
                  }
                ],
                "method": "POST",
                "body": {
                  "mode": "raw",
                  "raw": "{\n  \"id\": \"<string>\"\n}",
                  "options": {
                    "raw": {
                      "language": "json"
                    }
                  }
                }
              },
              "status": "OK",
              "code": 200,
              "header": [
                {
                  "key": "Content-Type",
                  "value": "text/plain"
                }
              ],
              "body": "",
              "cookie": [],
              "_postman_previewlanguage": "text"
            }
          ],
          "event": [],
          "protocolProfileBehavior": {
            "disableBodyPruning": true
          }
        },
        {
          "id": "7aaeeb94-edd3-43fd-9c20-feb111c32b6b",
          "name": "Viam List Data Pipeline Runs",
          "request": {
            "name": "Viam List Data Pipeline Runs",
            "description": {
              "content": "List historical runs for a data pipeline.",
              "type": "text/plain"
            },
            "url": {
              "path": [
                "viam.app.datapipelines.v1.DataPipelinesService",
                "ListDataPipelineRuns"
              ],
              "host": [
                "{{baseUrl}}"
              ],
              "query": [],
              "variable": []
            },
            "header": [
              {
                "key": "Content-Type",
                "value": "application/json"
              }
            ],
            "method": "POST",
            "auth": null,
            "body": {
              "mode": "raw",
              "raw": "{\n  \"id\": \"<string>\",\n  \"page_size\": \"<integer>\",\n  \"page_token\": \"<string>\"\n}",
              "options": {
                "raw": {
                  "language": "json"
                }
              }
            }
          },
          "response": [
            {
              "id": "214d802d-c919-4e0f-b9ee-4b3a226ce2e7",
              "name": "Successful response.",
              "originalRequest": {
                "url": {
                  "path": [
                    "viam.app.datapipelines.v1.DataPipelinesService",
                    "ListDataPipelineRuns"
                  ],
                  "host": [
                    "{{baseUrl}}"
                  ],
                  "query": [],
                  "variable": []
                },
                "header": [
                  {
                    "description": {
                      "content": "Added as a part of security scheme: apikey",
                      "type": "text/plain"
                    },
                    "key": "key",
                    "value": "<API Key>"
                  }
                ],
                "method": "POST",
                "body": {
                  "mode": "raw",
                  "raw": "{\n  \"id\": \"<string>\",\n  \"page_size\": \"<integer>\",\n  \"page_token\": \"<string>\"\n}",
                  "options": {
                    "raw": {
                      "language": "json"
                    }
                  }
                }
              },
              "status": "OK",
              "code": 200,
              "header": [
                {
                  "key": "Content-Type",
                  "value": "text/plain"
                }
              ],
              "body": "",
              "cookie": [],
              "_postman_previewlanguage": "text"
            }
          ],
          "event": [],
          "protocolProfileBehavior": {
            "disableBodyPruning": true
          }
        }
      ],
      "event": []
    }
  ],
  "event": [],
  "variable": [
    {
      "type": "string",
      "value": "https://app.viam.com",
      "key": "baseUrl"
    }
  ],
  "auth": {
    "type": "apikey",
    "apikey": [
      {
        "key": "key",
        "value": "key"
      },
      {
        "key": "value",
        "value": "{{apiKey}}"
      },
      {
        "key": "in",
        "value": "header"
      }
    ]
  },
  "info": {
    "_postman_id": "81bc25f7-9b7c-469b-a6e2-81282d96c251",
    "name": "Viam Data Pipelines API",
    "schema": "https://schema.getpostman.com/json/collection/v2.1.0/collection.json",
    "description": {
      "content": "REST/JSON transcoding of the Viam DataPipelinesService gRPC API. Create, list, rename,\nenable, disable, and delete scheduled MQL data pipelines that aggregate captured\nmachine data into the Viam hot data store.\n\nCanonical contract: https://github.com/viamrobotics/api/blob/main/proto/viam/app/datapipelines/v1/data_pipelines.proto\n\n\nContact Support:\n Name: Viam Support",
      "type": "text/plain"
    }
  }
}